prestans/__init__.py
prestans/deserializer.py
prestans/exception.py
prestans/http.py
prestans/serializer.py
prestans/util.py
prestans/bin/__init__.py
prestans/bin/pride.py
prestans/devel/__init__.py
prestans/devel/exception.py
prestans/devel/gen/__init__.py
prestans/devel/gen/closure.py
prestans/devel/gen/templates/__init__.py
prestans/devel/gen/templates/closure/__init__.py
prestans/devel/gen/templates/closure/filter/__init__.py
prestans/devel/gen/templates/closure/filter/filter.jinja
prestans/devel/gen/templates/closure/filter/macro.jinja
prestans/devel/gen/templates/closure/model/__init__.py
prestans/devel/gen/templates/closure/model/macro.jinja
prestans/devel/gen/templates/closure/model/model.jinja
prestans/ext/__init__.py
prestans/ext/appengine.py
prestans/ext/data/__init__.py
prestans/ext/data/adapters/__init__.py
prestans/ext/data/adapters/ndb.py
prestans/ext/data/adapters/sqlalchemy.py
prestans/parser/__init__.py
prestans/parser/attribute_filter.py
prestans/parser/attribute_filter_immutable.py
prestans/parser/config.py
prestans/parser/parameter_set.py
prestans/parser/verb_config.py
prestans/provider/__init__.py
prestans/provider/auth.py
prestans/provider/cache.py
prestans/provider/throttle.py
prestans/rest/__init__.py
prestans/rest/blueprint_handler.py
prestans/rest/dictionary_response.py
prestans/rest/error_response.py
prestans/rest/request.py
prestans/rest/request_handler.py
prestans/rest/request_router.py
prestans/rest/response.py
prestans/types/__init__.py
prestans/types/array.py
prestans/types/base.py
prestans/types/binary_response.py
prestans/types/boolean.py
prestans/types/data_url_file.py
prestans/types/date.py
prestans/types/datetime_prestans.py
prestans/types/float.py
prestans/types/integer.py
prestans/types/model.py
prestans/types/string_prestans.py
prestans/types/time_prestans.py
prestans-2.5.4.dist-info/METADATA
prestans-2.5.4.dist-info/RECORD
prestans-2.5.4.dist-info/WHEEL
prestans-2.5.4.dist-info/entry_points.txt
prestans-2.5.4.dist-info/top_level.txt
