Metadata-Version: 2.1
Name: prestans
Version: 2.5.4
Summary: A WSGI compliant REST micro-framework
Home-page: https://github.com/anomaly/prestans.git
Author: Anomaly Software
Author-email: support@anomaly.net.au
Maintainer: Anomaly Software
Maintainer-email: support@anomaly.net.au
License: New BSD
Download-URL: https://github.com/anomaly/prestans/archive/2.5.4.tar.gz
Platform: any
Classifier: Environment :: Web Environment
Classifier: Intended Audience :: Developers
Classifier: Operating System :: OS Independent
Classifier: Programming Language :: Python
Classifier: Programming Language :: Python :: 2.7
Classifier: Topic :: Internet :: WWW/HTTP
Classifier: Topic :: Internet :: WWW/HTTP :: WSGI
Classifier: Topic :: Software Development :: Libraries :: Application Frameworks
Classifier: Topic :: Software Development :: Libraries :: Python Modules
Provides-Extra: devel
Requires-Dist: WebOb (>=1.7)
Provides-Extra: devel
Requires-Dist: Jinja2; extra == 'devel'
